faketory/__init__.py
faketory/factory.py
faketory/gens.py
faketory/placeholders/models.py
faketory-0.1.2.dist-info/LICENSE
faketory-0.1.2.dist-info/WHEEL
faketory-0.1.2.dist-info/METADATA
faketory-0.1.2.dist-info/RECORD
