Metadata-Version: 2.1
Name: faketory
Version: 0.1.2
Summary: A very simple Factory library. Generic, but compatible with Django. Let's build together!
Home-page: https://github.com/warevil/faketory
Author: warevil
Author-email: jg@warevil.dev
Requires-Python: >=3.7,<4.0
Classifier: Programming Language :: Python :: 3
Classifier: Programming Language :: Python :: 3.7
Classifier: Programming Language :: Python :: 3.8
Classifier: Programming Language :: Python :: 3.9
Classifier: Programming Language :: Python :: 3.10
Classifier: Programming Language :: Python :: 3.11
Requires-Dist: faker (>=15.1.1,<16.0.0)
Project-URL: Repository, https://github.com/warevil/faketory
